django_toots/__init__.py
django_toots/admin.py
django_toots/api.py
django_toots/apps.py
django_toots/decorators.py
django_toots/exceptions.py
django_toots/models.py
django_toots/migrations/0001_initial.py
django_toots/migrations/0002_remove_tootfile_expires_at_and_more.py
django_toots/migrations/__init__.py
django_toots-0.0.1.dist-info/LICENSE
django_toots-0.0.1.dist-info/METADATA
django_toots-0.0.1.dist-info/WHEEL
django_toots-0.0.1.dist-info/top_level.txt
django_toots-0.0.1.dist-info/RECORD
