Metadata-Version: 2.1
Name: django-toots
Version: 0.0.1
Summary: An app to manage toots (Mastodon posts) in a Django project
Author-email: Rami <ramiboutas@protonmail.com>
Project-URL: Homepage, https://github.com/ramiboutas/django-toots
Project-URL: Bug Tracker, https://github.com/ramiboutas/django-toots/issues
Classifier: Development Status :: 1 - Planning
Classifier: Programming Language :: Python :: 3
Classifier: License :: OSI Approved :: MIT License
Classifier: Operating System :: OS Independent
Classifier: Framework :: Django
Classifier: Framework :: Django :: 4
Requires-Python: >=3.7
License-File: LICENSE
Requires-Dist: Mastodon.py
Requires-Dist: django
